poi_spider/__init__.py
poi_spider-0.0.1.dist-info/METADATA
poi_spider-0.0.1.dist-info/WHEEL
poi_spider-0.0.1.dist-info/top_level.txt
poi_spider-0.0.1.dist-info/RECORD
