Metadata-Version: 2.1
Name: poi-spider
Version: 0.0.1
Summary: an useful tool for getting poi data from baidu
Home-page: https://github.com/xugongli/baidu-poi
Author: soaringsoul
Author-email: 951683309@qq.com
License: UNKNOWN
Platform: UNKNOWN
Classifier: Programming Language :: Python :: 3
Classifier: License :: OSI Approved :: MIT License
Classifier: Operating System :: OS Independent
Requires-Python: >=3.6
